extra_streamlit_tools/__init__.py
extra_streamlit_tools/_logging.py
extra_streamlit_tools/data.py
extra_streamlit_tools/utils.py
extra_streamlit_tools-0.2.0.dist-info/LICENSE
extra_streamlit_tools-0.2.0.dist-info/METADATA
extra_streamlit_tools-0.2.0.dist-info/WHEEL
extra_streamlit_tools-0.2.0.dist-info/RECORD
