Metadata-Version: 2.1
Name: extra-streamlit-tools
Version: 0.2.0
Summary: Extra tools to use for streamlit applications
Author: Tomer Gabay
Author-email: tomergabay001@gmail.com
Requires-Python: >=3.9, !=2.7.*, !=3.0.*, !=3.1.*, !=3.2.*, !=3.3.*, !=3.4.*, !=3.5.*, !=3.6.*, !=3.7.*, !=3.8.*
Classifier: Programming Language :: Python :: 3
Classifier: Programming Language :: Python :: 3.9
Classifier: Programming Language :: Python :: 3.10
Classifier: Programming Language :: Python :: 3.11
Requires-Dist: streamlit (>=1.20.0,<2.0.0)
